{"timestamp":1764533862939,"settings":[{"key":"app.7tv.token","type":"string","value":"","timestamp":1764533604345},{"key":"chat.ignore_clear_chat","type":"boolean","value":false,"timestamp":1764533712541},{"key":"chat.message_batch_duration","type":"number","value":150,"timestamp":1737237196559},{"key":"chat_input.spam.bypass_duplicate","type":"boolean","value":true,"timestamp":1764533760243},{"key":"general.autoclaim.channel_points","type":"boolean","value":true,"timestamp":1737237383251},{"key":"highlights.basic.mention_sound","type":"boolean","value":true,"timestamp":1764533792056},{"key":"highlights.basic.mention_title_flash","type":"boolean","value":true,"timestamp":1737237196559},{"key":"highlights.custom","type":"object","value":[],"timestamp":1764490071280,"constructorName":"Map"},{"key":"layout.hide_unfollow_button","type":"boolean","value":true,"timestamp":1753606765271},{"key":"player.video_stats","type":"boolean","value":true,"timestamp":1764533620960}]}